bluetti_bt_lib/__init__.py
bluetti_bt_lib/const.py
bluetti_bt_lib/base_devices/__init__.py
bluetti_bt_lib/base_devices/base_device_v1.py
bluetti_bt_lib/base_devices/base_device_v2.py
bluetti_bt_lib/base_devices/bluetti_device.py
bluetti_bt_lib/bluetooth/__init__.py
bluetti_bt_lib/bluetooth/device_reader.py
bluetti_bt_lib/bluetooth/device_recognizer.py
bluetti_bt_lib/bluetooth/device_writer.py
bluetti_bt_lib/bluetooth/encryption.py
bluetti_bt_lib/devices/__init__.py
bluetti_bt_lib/devices/ac180.py
bluetti_bt_lib/devices/ac180p.py
bluetti_bt_lib/devices/ac180t.py
bluetti_bt_lib/devices/ac200l.py
bluetti_bt_lib/devices/ac200m.py
bluetti_bt_lib/devices/ac200pl.py
bluetti_bt_lib/devices/ac2a.py
bluetti_bt_lib/devices/ac2p.py
bluetti_bt_lib/devices/ac300.py
bluetti_bt_lib/devices/ac500.py
bluetti_bt_lib/devices/ac50b.py
bluetti_bt_lib/devices/ac60.py
bluetti_bt_lib/devices/ac60p.py
bluetti_bt_lib/devices/ac70.py
bluetti_bt_lib/devices/ac70p.py
bluetti_bt_lib/devices/ap300.py
bluetti_bt_lib/devices/eb3a.py
bluetti_bt_lib/devices/el100v2.py
bluetti_bt_lib/devices/el30v2.py
bluetti_bt_lib/devices/ep2000.py
bluetti_bt_lib/devices/ep500.py
bluetti_bt_lib/devices/ep500p.py
bluetti_bt_lib/devices/ep600.py
bluetti_bt_lib/devices/ep760.py
bluetti_bt_lib/devices/ep800.py
bluetti_bt_lib/devices/handsfree1.py
bluetti_bt_lib/devices/pr30v2.py
bluetti_bt_lib/enums/__init__.py
bluetti_bt_lib/enums/charging_mode.py
bluetti_bt_lib/enums/display_mode.py
bluetti_bt_lib/enums/eco_mode.py
bluetti_bt_lib/enums/frequency_mode.py
bluetti_bt_lib/enums/led_mode.py
bluetti_bt_lib/enums/output_mode.py
bluetti_bt_lib/enums/split_phase_mode.py
bluetti_bt_lib/enums/ups_mode.py
bluetti_bt_lib/fields/BoolField.py
bluetti_bt_lib/fields/BoolFieldNonZero.py
bluetti_bt_lib/fields/DecimalArrayField.py
bluetti_bt_lib/fields/DecimalField.py
bluetti_bt_lib/fields/DeviceField.py
bluetti_bt_lib/fields/EnumField.py
bluetti_bt_lib/fields/FieldName.py
bluetti_bt_lib/fields/FieldUnit.py
bluetti_bt_lib-0.1.6.dist-info/licenses/LICENSE
bluetti_bt_lib-0.1.6.dist-info/METADATA
bluetti_bt_lib-0.1.6.dist-info/WHEEL
bluetti_bt_lib-0.1.6.dist-info/entry_points.txt
bluetti_bt_lib-0.1.6.dist-info/top_level.txt
bluetti_bt_lib-0.1.6.dist-info/RECORD
