Metadata-Version: 2.4
Name: bluetti-bt-lib
Version: 0.1.6
Summary: Bluetti BT
Home-page: https://github.com/Patrick762/bluetti-bt-lib
Author: Patrick762
Author-email: <pip-bluetti-bt-lib@hosting-rt.de>
Classifier: Development Status :: 4 - Beta
Classifier: Intended Audience :: Developers
Classifier: Programming Language :: Python :: 3
License-File: LICENSE
Requires-Dist: async_timeout
Requires-Dist: asyncio
Requires-Dist: bleak
Requires-Dist: bleak_retry_connector
Requires-Dist: crcmod
Requires-Dist: cryptography
Requires-Dist: logging
Requires-Dist: pyasn1
Dynamic: author
Dynamic: author-email
Dynamic: classifier
Dynamic: description
Dynamic: description-content-type
Dynamic: home-page
Dynamic: license-file
Dynamic: requires-dist
Dynamic: summary
